{
	"Name": "Devspair",
	"Location": "Spain",
	"Id": "Devspair-Team",
	"Email": "Devspair@protonmail.com",
	"Description": "Team with the aims to master coding while providing the community with open source projects",
	"Team": {
		"TheWisker": {
			"Role": "Owner",
			"Url": "https://github.com/TheWisker",
			"Email": "TheWisker@protonmail.com"
		},
		"Backest": {
			"Role": "Owner",
			"Url": "https://github.com/Backist",
			"Email": "alvarodrumer54@gmail.com"
		}
	},
	"Projects": {
		".github": {
			"Creator": "Devspair",
			"Description": "Public data in the organization",
			"Tags": ["organization", "dataspace", "devspair"]	
		},
		"Notes": {
			"Creator": "Devspair",
			"Description": "Advanced markdown-able note-taking rust application",
			"Tags": ["note", "desktop", "rust", "advanced", "markdown"]	
		}
	}
}
